[{"playerId":"rd48","ranking":835,"points":19,"tournamentPlayed":19},{"playerId":"g585","ranking":390,"points":102,"tournamentPlayed":21},{"playerId":"rb00","ranking":837,"points":19,"tournamentPlayed":21},{"playerId":"mn70","ranking":540,"points":58,"tournamentPlayed":18},{"playerId":"sx90","ranking":486,"points":71,"tournamentPlayed":28},{"playerId":"gf95","ranking":402,"points":97,"tournamentPlayed":24},{"playerId":"sx91","ranking":622,"points":44,"tournamentPlayed":9},{"playerId":"hg86","ranking":289,"points":169,"tournamentPlayed":22},{"playerId":"gb13","ranking":884,"points":16,"tournamentPlayed":18},{"playerId":"da89","ranking":408,"points":96,"tournamentPlayed":26},{"playerId":"da85","ranking":525,"points":61,"tournamentPlayed":20},{"playerId":"da86","ranking":318,"points":150,"tournamentPlayed":16},{"playerId":"da81","ranking":104,"points":539,"tournamentPlayed":26},{"playerId":"rd34","ranking":907,"points":14,"tournamentPlayed":11},{"playerId":"sg64","ranking":233,"points":223,"tournamentPlayed":29},{"playerId":"fc49","ranking":765,"points":24,"tournamentPlayed":18},{"playerId":"sx77","ranking":970,"points":11,"tournamentPlayed":9},{"playerId":"t742","ranking":149,"points":376,"tournamentPlayed":13},{"playerId":"t984","ranking":921,"points":13,"tournamentPlayed":6},{"playerId":"i306","ranking":279,"points":180,"tournamentPlayed":30},{"playerId":"l0aq","ranking":948,"points":12,"tournamentPlayed":11},{"playerId":"rd67","ranking":864,"points":17,"tournamentPlayed":16},{"playerId":"hc21","ranking":774,"points":23,"tournamentPlayed":12},{"playerId":"e180","ranking":844,"points":18,"tournamentPlayed":3},{"playerId":"ml48","ranking":649,"points":38,"tournamentPlayed":26},{"playerId":"v717","ranking":154,"points":355,"tournamentPlayed":30},{"playerId":"a829","ranking":91,"points":608,"tournamentPlayed":30},{"playerId":"fa43","ranking":373,"points":111,"tournamentPlayed":30},{"playerId":"mj08","ranking":96,"points":575,"tournamentPlayed":28},{"playerId":"h693","ranking":831,"points":19,"tournamentPlayed":17},{"playerId":"k964","ranking":333,"points":141,"tournamentPlayed":26},{"playerId":"st29","ranking":778,"points":23,"tournamentPlayed":21},{"playerId":"k966","ranking":150,"points":376,"tournamentPlayed":19},{"playerId":"i305","ranking":192,"points":281,"tournamentPlayed":18},{"playerId":"bj05","ranking":469,"points":77,"tournamentPlayed":26},{"playerId":"gd61","ranking":551,"points":56,"tournamentPlayed":28},{"playerId":"hg94","ranking":507,"points":66,"tournamentPlayed":15},{"playerId":"gd64","ranking":297,"points":164,"tournamentPlayed":20},{"playerId":"mj01","ranking":613,"points":45,"tournamentPlayed":18},{"playerId":"mn85","ranking":821,"points":19,"tournamentPlayed":5},{"playerId":"a0ao","ranking":947,"points":12,"tournamentPlayed":10},{"playerId":"ml35","ranking":818,"points":20,"tournamentPlayed":24},{"playerId":"fa33","ranking":754,"points":25,"tournamentPlayed":20},{"playerId":"sx96","ranking":786,"points":22,"tournamentPlayed":16},{"playerId":"v942","ranking":789,"points":21,"tournamentPlayed":4},{"playerId":"j620","ranking":303,"points":160,"tournamentPlayed":26},{"playerId":"v708","ranking":60,"points":850,"tournamentPlayed":26},{"playerId":"bj37","ranking":700,"points":30,"tournamentPlayed":23},{"playerId":"gd91","ranking":357,"points":120,"tournamentPlayed":24},{"playerId":"bl78","ranking":814,"points":20,"tournamentPlayed":17},{"playerId":"r383","ranking":433,"points":87,"tournamentPlayed":18},{"playerId":"ml73","ranking":876,"points":16,"tournamentPlayed":9},{"playerId":"gb53","ranking":292,"points":166,"tournamentPlayed":24},{"playerId":"kh56","ranking":220,"points":241,"tournamentPlayed":36},{"playerId":"kf15","ranking":672,"points":33,"tournamentPlayed":8},{"playerId":"li39","ranking":753,"points":25,"tournamentPlayed":17},{"playerId":"t315","ranking":520,"points":62,"tournamentPlayed":7},{"playerId":"se73","ranking":41,"points":1235,"tournamentPlayed":27},{"playerId":"i326","ranking":733,"points":26,"tournamentPlayed":11},{"playerId":"m915","ranking":257,"points":198,"tournamentPlayed":18},{"playerId":"tf58","ranking":246,"points":209,"tournamentPlayed":24},{"playerId":"gb41","ranking":773,"points":23,"tournamentPlayed":12},{"playerId":"gb42","ranking":646,"points":38,"tournamentPlayed":9},{"playerId":"gd84","ranking":697,"points":30,"tournamentPlayed":12},{"playerId":"bl60","ranking":526,"points":61,"tournamentPlayed":21},{"playerId":"ml57","ranking":416,"points":92,"tournamentPlayed":19},{"playerId":"t786","ranking":19,"points":2050,"tournamentPlayed":19},{"playerId":"fa50","ranking":724,"points":27,"tournamentPlayed":20},{"playerId":"j400","ranking":365,"points":115,"tournamentPlayed":28},{"playerId":"j647","ranking":906,"points":14,"tournamentPlayed":4},{"playerId":"j439","ranking":687,"points":31,"tournamentPlayed":13},{"playerId":"sc56","ranking":100,"points":550,"tournamentPlayed":22},{"playerId":"ml91","ranking":561,"points":54,"tournamentPlayed":19},{"playerId":"td47","ranking":395,"points":99,"tournamentPlayed":18},{"playerId":"gb71","ranking":401,"points":98,"tournamentPlayed":29},{"playerId":"tb05","ranking":928,"points":13,"tournamentPlayed":12},{"playerId":"kh75","ranking":642,"points":40,"tournamentPlayed":34},{"playerId":"ml93","ranking":981,"points":11,"tournamentPlayed":18},{"playerId":"v762","ranking":569,"points":53,"tournamentPlayed":19},{"playerId":"kf31","ranking":770,"points":24,"tournamentPlayed":28},{"playerId":"ha28","ranking":342,"points":132,"tournamentPlayed":23},{"playerId":"v758","ranking":631,"points":42,"tournamentPlayed":23},{"playerId":"a622","ranking":228,"points":229,"tournamentPlayed":35},{"playerId":"k767","ranking":684,"points":32,"tournamentPlayed":24},{"playerId":"w609","ranking":847,"points":18,"tournamentPlayed":10},{"playerId":"rb60","ranking":381,"points":106,"tournamentPlayed":20},{"playerId":"bh08","ranking":514,"points":65,"tournamentPlayed":33},{"playerId":"bh09","ranking":51,"points":968,"tournamentPlayed":21},{"playerId":"cm79","ranking":426,"points":89,"tournamentPlayed":23},{"playerId":"rb56","ranking":141,"points":405,"tournamentPlayed":29},{"playerId":"bh02","ranking":475,"points":75,"tournamentPlayed":27},{"playerId":"sc47","ranking":161,"points":339,"tournamentPlayed":22},{"playerId":"gb61","ranking":186,"points":300,"tournamentPlayed":21},{"playerId":"s483","ranking":123,"points":467,"tournamentPlayed":20},{"playerId":"bl82","ranking":417,"points":92,"tournamentPlayed":35},{"playerId":"v750","ranking":586,"points":51,"tournamentPlayed":26},{"playerId":"kf24","ranking":788,"points":22,"tournamentPlayed":19},{"playerId":"z09k","ranking":775,"points":23,"tournamentPlayed":15},{"playerId":"v505","ranking":512,"points":65,"tournamentPlayed":19},{"playerId":"kf17","ranking":184,"points":301,"tournamentPlayed":17},{"playerId":"i330","ranking":400,"points":98,"tournamentPlayed":24},{"playerId":"a853","ranking":209,"points":253,"tournamentPlayed":21},{"playerId":"mj71","ranking":174,"points":316,"tournamentPlayed":28},{"playerId":"rb89","ranking":828,"points":19,"tournamentPlayed":12},{"playerId":"mj70","ranking":258,"points":198,"tournamentPlayed":28},{"playerId":"gb93","ranking":134,"points":435,"tournamentPlayed":32},{"playerId":"sc77","ranking":117,"points":498,"tournamentPlayed":28},{"playerId":"gb94","ranking":597,"points":48,"tournamentPlayed":21},{"playerId":"le01","ranking":206,"points":258,"tournamentPlayed":33},{"playerId":"w630","ranking":252,"points":201,"tournamentPlayed":21},{"playerId":"mh30","ranking":103,"points":541,"tournamentPlayed":21},{"playerId":"v784","ranking":636,"points":40,"tournamentPlayed":16},{"playerId":"ha47","ranking":648,"points":38,"tournamentPlayed":24},{"playerId":"kd14","ranking":768,"points":24,"tournamentPlayed":23},{"playerId":"bj70","ranking":667,"points":34,"tournamentPlayed":14},{"playerId":"mj69","ranking":829,"points":19,"tournamentPlayed":14},{"playerId":"d916","ranking":293,"points":166,"tournamentPlayed":30},{"playerId":"d917","ranking":392,"points":101,"tournamentPlayed":19},{"playerId":"l872","ranking":814,"points":20,"tournamentPlayed":17},{"playerId":"sp05","ranking":495,"points":69,"tournamentPlayed":31},{"playerId":"d915","ranking":957,"points":12,"tournamentPlayed":16},{"playerId":"sc73","ranking":105,"points":531,"tournamentPlayed":32},{"playerId":"a887","ranking":212,"points":251,"tournamentPlayed":22},{"playerId":"tb20","ranking":474,"points":75,"tournamentPlayed":23},{"playerId":"rb86","ranking":531,"points":60,"tournamentPlayed":22},{"playerId":"mw02","ranking":140,"points":406,"tournamentPlayed":25},{"playerId":"td55","ranking":406,"points":96,"tournamentPlayed":19},{"playerId":"n0b4","ranking":923,"points":13,"tournamentPlayed":7},{"playerId":"ag37","ranking":168,"points":327,"tournamentPlayed":18},{"playerId":"ci14","ranking":270,"points":190,"tournamentPlayed":21},{"playerId":"bh22","ranking":461,"points":78,"tournamentPlayed":23},{"playerId":"ha33","ranking":776,"points":23,"tournamentPlayed":18},{"playerId":"gb88","ranking":7,"points":3400,"tournamentPlayed":25},{"playerId":"ha37","ranking":943,"points":12,"tournamentPlayed":7},{"playerId":"mh16","ranking":144,"points":396,"tournamentPlayed":24},{"playerId":"w614","ranking":465,"points":78,"tournamentPlayed":26},{"playerId":"w857","ranking":543,"points":58,"tournamentPlayed":21},{"playerId":"k771","ranking":322,"points":149,"tournamentPlayed":33},{"playerId":"rb73","ranking":515,"points":64,"tournamentPlayed":22},{"playerId":"td51","ranking":98,"points":569,"tournamentPlayed":25},{"playerId":"k776","ranking":300,"points":161,"tournamentPlayed":23},{"playerId":"c813","ranking":324,"points":147,"tournamentPlayed":31},{"playerId":"cg07","ranking":315,"points":154,"tournamentPlayed":27},{"playerId":"ci49","ranking":1000,"points":10,"tournamentPlayed":8},{"playerId":"cg04","ranking":276,"points":183,"tournamentPlayed":20},{"playerId":"kd35","ranking":566,"points":53,"tournamentPlayed":12},{"playerId":"kd32","ranking":792,"points":21,"tournamentPlayed":11},{"playerId":"bf12","ranking":476,"points":73,"tournamentPlayed":20},{"playerId":"mj98","ranking":366,"points":114,"tournamentPlayed":20},{"playerId":"bj92","ranking":830,"points":19,"tournamentPlayed":17},{"playerId":"d939","ranking":662,"points":35,"tournamentPlayed":22},{"playerId":"sp25","ranking":669,"points":34,"tournamentPlayed":19},{"playerId":"n830","ranking":903,"points":15,"tournamentPlayed":22},{"playerId":"sr69","ranking":736,"points":26,"tournamentPlayed":12},{"playerId":"d935","ranking":685,"points":32,"tournamentPlayed":25},{"playerId":"j476","ranking":686,"points":32,"tournamentPlayed":26},{"playerId":"l899","ranking":644,"points":39,"tournamentPlayed":23},{"playerId":"v555","ranking":423,"points":90,"tournamentPlayed":23},{"playerId":"sp24","ranking":199,"points":270,"tournamentPlayed":23},{"playerId":"ae14","ranking":253,"points":200,"tournamentPlayed":20},{"playerId":"hc99","ranking":364,"points":116,"tournamentPlayed":30},{"playerId":"mj89","ranking":524,"points":61,"tournamentPlayed":16},{"playerId":"mj88","ranking":536,"points":59,"tournamentPlayed":22},{"playerId":"sp18","ranking":819,"points":20,"tournamentPlayed":26},{"playerId":"f09j","ranking":900,"points":15,"tournamentPlayed":14},{"playerId":"b747","ranking":55,"points":911,"tournamentPlayed":19},{"playerId":"v306","ranking":40,"points":1260,"tournamentPlayed":25},{"playerId":"d923","ranking":29,"points":1490,"tournamentPlayed":29},{"playerId":"n824","ranking":739,"points":26,"tournamentPlayed":19},{"playerId":"dh18","ranking":901,"points":15,"tournamentPlayed":17},{"playerId":"tb69","ranking":6,"points":4060,"tournamentPlayed":25},{"playerId":"kb14","ranking":183,"points":303,"tournamentPlayed":23},{"playerId":"mf35","ranking":130,"points":446,"tournamentPlayed":22},{"playerId":"kb12","ranking":782,"points":23,"tournamentPlayed":23},{"playerId":"ha89","ranking":989,"points":11,"tournamentPlayed":22},{"playerId":"bh76","ranking":370,"points":112,"tournamentPlayed":20},{"playerId":"bh80","ranking":336,"points":139,"tournamentPlayed":22},{"playerId":"kb09","ranking":172,"points":317,"tournamentPlayed":23},{"playerId":"m762","ranking":317,"points":150,"tournamentPlayed":5},{"playerId":"j493","ranking":267,"points":192,"tournamentPlayed":35},{"playerId":"i165","ranking":73,"points":733,"tournamentPlayed":24},{"playerId":"bu13","ranking":659,"points":35,"tournamentPlayed":10},{"playerId":"ha71","ranking":256,"points":199,"tournamentPlayed":25},{"playerId":"bf27","ranking":537,"points":59,"tournamentPlayed":23},{"playerId":"kd46","ranking":216,"points":245,"tournamentPlayed":8},{"playerId":"kd43","ranking":567,"points":53,"tournamentPlayed":16},{"playerId":"bf23","ranking":190,"points":287,"tournamentPlayed":24},{"playerId":"le38","ranking":803,"points":21,"tournamentPlayed":21},{"playerId":"sr81","ranking":945,"points":12,"tournamentPlayed":10},{"playerId":"kb05","ranking":38,"points":1283,"tournamentPlayed":26},{"playerId":"kd48","ranking":755,"points":25,"tournamentPlayed":21},{"playerId":"sr79","ranking":534,"points":59,"tournamentPlayed":19},{"playerId":"a678","ranking":11,"points":2620,"tournamentPlayed":23},{"playerId":"k336","ranking":89,"points":635,"tournamentPlayed":22},{"playerId":"n607","ranking":688,"points":31,"tournamentPlayed":15},{"playerId":"kd70","ranking":230,"points":227,"tournamentPlayed":25},{"playerId":"kd71","ranking":549,"points":57,"tournamentPlayed":29},{"playerId":"c882","ranking":32,"points":1380,"tournamentPlayed":25},{"playerId":"ac28","ranking":851,"points":18,"tournamentPlayed":17},{"playerId":"sp77","ranking":727,"points":27,"tournamentPlayed":23},{"playerId":"kb37","ranking":196,"points":275,"tournamentPlayed":33},{"playerId":"cg47","ranking":988,"points":11,"tournamentPlayed":21},{"playerId":"bf55","ranking":112,"points":506,"tournamentPlayed":21},{"playerId":"lc23","ranking":958,"points":12,"tournamentPlayed":17},{"playerId":"bh98","ranking":941,"points":12,"tournamentPlayed":3},{"playerId":"i183","ranking":869,"points":17,"tournamentPlayed":21},{"playerId":"i186","ranking":18,"points":2230,"tournamentPlayed":24},{"playerId":"bu34","ranking":680,"points":32,"tournamentPlayed":15},{"playerId":"sa93","ranking":81,"points":686,"tournamentPlayed":26},{"playerId":"d960","ranking":966,"points":11,"tournamentPlayed":7},{"playerId":"lc11","ranking":344,"points":127,"tournamentPlayed":22},{"playerId":"bd06","ranking":23,"points":1845,"tournamentPlayed":24},{"playerId":"tb79","ranking":863,"points":17,"tournamentPlayed":15},{"playerId":"cg33","ranking":273,"points":188,"tournamentPlayed":26},{"playerId":"lc12","ranking":428,"points":88,"tournamentPlayed":16},{"playerId":"bh87","ranking":312,"points":156,"tournamentPlayed":22},{"playerId":"lc18","ranking":632,"points":42,"tournamentPlayed":27},{"playerId":"cg32","ranking":244,"points":212,"tournamentPlayed":26},{"playerId":"tb70","ranking":460,"points":78,"tournamentPlayed":23},{"playerId":"k596","ranking":635,"points":41,"tournamentPlayed":13},{"playerId":"j267","ranking":118,"points":495,"tournamentPlayed":32},{"playerId":"mw54","ranking":937,"points":13,"tournamentPlayed":21},{"playerId":"e811","ranking":577,"points":52,"tournamentPlayed":29},{"playerId":"d750","ranking":157,"points":347,"tournamentPlayed":26},{"playerId":"mf71","ranking":626,"points":43,"tournamentPlayed":9},{"playerId":"c660","ranking":717,"points":27,"tournamentPlayed":10},{"playerId":"kb54","ranking":127,"points":446,"tournamentPlayed":23},{"playerId":"dh58","ranking":142,"points":401,"tournamentPlayed":20},{"playerId":"ce25","ranking":188,"points":291,"tournamentPlayed":31},{"playerId":"dh55","ranking":691,"points":31,"tournamentPlayed":25},{"playerId":"cg64","ranking":482,"points":72,"tournamentPlayed":34},{"playerId":"sn54","ranking":354,"points":120,"tournamentPlayed":20},{"playerId":"pg04","ranking":574,"points":52,"tournamentPlayed":18},{"playerId":"cg63","ranking":780,"points":23,"tournamentPlayed":22},{"playerId":"sl08","ranking":54,"points":928,"tournamentPlayed":31},{"playerId":"sl07","ranking":272,"points":189,"tournamentPlayed":26},{"playerId":"gk24","ranking":860,"points":17,"tournamentPlayed":12},{"playerId":"sl09","ranking":361,"points":117,"tournamentPlayed":13},{"playerId":"gk25","ranking":758,"points":25,"tournamentPlayed":24},{"playerId":"q927","ranking":12,"points":2490,"tournamentPlayed":23},{"playerId":"n897","ranking":217,"points":245,"tournamentPlayed":20},{"playerId":"bu54","ranking":278,"points":181,"tournamentPlayed":27},{"playerId":"d752","ranking":489,"points":70,"tournamentPlayed":18},{"playerId":"o507","ranking":725,"points":27,"tournamentPlayed":21},{"playerId":"d981","ranking":197,"points":273,"tournamentPlayed":24},{"playerId":"sp80","ranking":298,"points":164,"tournamentPlayed":31},{"playerId":"kb43","ranking":412,"points":94,"tournamentPlayed":21},{"playerId":"kd87","ranking":299,"points":163,"tournamentPlayed":22},{"playerId":"ci96","ranking":940,"points":12,"tournamentPlayed":3},{"playerId":"bd20","ranking":137,"points":431,"tournamentPlayed":20},{"playerId":"sn44","ranking":457,"points":79,"tournamentPlayed":26},{"playerId":"h09p","ranking":922,"points":13,"tournamentPlayed":6},{"playerId":"dh50","ranking":483,"points":71,"tournamentPlayed":12},{"playerId":"a479","ranking":178,"points":308,"tournamentPlayed":15},{"playerId":"mw76","ranking":909,"points":14,"tournamentPlayed":12},{"playerId":"mw75","ranking":954,"points":12,"tournamentPlayed":14},{"playerId":"d985","ranking":194,"points":279,"tournamentPlayed":20},{"playerId":"n409","ranking":1,"points":9760,"tournamentPlayed":17},{"playerId":"e830","ranking":396,"points":99,"tournamentPlayed":20},{"playerId":"e831","ranking":26,"points":1667,"tournamentPlayed":26},{"playerId":"pg20","ranking":254,"points":200,"tournamentPlayed":28},{"playerId":"sn70","ranking":826,"points":19,"tournamentPlayed":7},{"playerId":"md50","ranking":895,"points":15,"tournamentPlayed":11},{"playerId":"mf90","ranking":749,"points":25,"tournamentPlayed":6},{"playerId":"r0a5","ranking":737,"points":26,"tournamentPlayed":15},{"playerId":"mf95","ranking":949,"points":12,"tournamentPlayed":12},{"playerId":"aa27","ranking":618,"points":45,"tournamentPlayed":22},{"playerId":"md56","ranking":50,"points":974,"tournamentPlayed":21},{"playerId":"bf98","ranking":321,"points":149,"tournamentPlayed":27},{"playerId":"sn77","ranking":215,"points":247,"tournamentPlayed":27},{"playerId":"q941","ranking":261,"points":196,"tournamentPlayed":20},{"playerId":"cg94","ranking":490,"points":69,"tournamentPlayed":9},{"playerId":"n670","ranking":750,"points":25,"tournamentPlayed":6},{"playerId":"o522","ranking":211,"points":251,"tournamentPlayed":20},{"playerId":"n674","ranking":193,"points":280,"tournamentPlayed":31},{"playerId":"q948","ranking":316,"points":152,"tournamentPlayed":13},{"playerId":"n679","ranking":207,"points":254,"tournamentPlayed":24},{"playerId":"g806","ranking":594,"points":48,"tournamentPlayed":4},{"playerId":"e869","ranking":808,"points":20,"tournamentPlayed":11},{"playerId":"o527","ranking":931,"points":13,"tournamentPlayed":14},{"playerId":"bu78","ranking":926,"points":13,"tournamentPlayed":9},{"playerId":"o524","ranking":799,"points":21,"tournamentPlayed":20},{"playerId":"e865","ranking":313,"points":155,"tournamentPlayed":12},{"playerId":"d776","ranking":352,"points":121,"tournamentPlayed":14},{"playerId":"q945","ranking":785,"points":22,"tournamentPlayed":9},{"playerId":"f952","ranking":595,"points":48,"tournamentPlayed":14},{"playerId":"u061","ranking":501,"points":67,"tournamentPlayed":9},{"playerId":"le91","ranking":762,"points":24,"tournamentPlayed":12},{"playerId":"mb02","ranking":71,"points":739,"tournamentPlayed":22},{"playerId":"lc54","ranking":467,"points":78,"tournamentPlayed":32},{"playerId":"aa19","ranking":977,"points":11,"tournamentPlayed":13},{"playerId":"lc58","ranking":451,"points":81,"tournamentPlayed":21},{"playerId":"ac58","ranking":846,"points":18,"tournamentPlayed":4},{"playerId":"sl28","ranking":56,"points":905,"tournamentPlayed":32},{"playerId":"pg13","ranking":678,"points":33,"tournamentPlayed":32},{"playerId":"w483","ranking":388,"points":104,"tournamentPlayed":17},{"playerId":"ac56","ranking":982,"points":11,"tournamentPlayed":18},{"playerId":"gk30","ranking":557,"points":55,"tournamentPlayed":25},{"playerId":"n661","ranking":578,"points":51,"tournamentPlayed":12},{"playerId":"cg80","ranking":46,"points":1036,"tournamentPlayed":27},{"playerId":"n663","ranking":411,"points":95,"tournamentPlayed":22},{"playerId":"p605","ranking":674,"points":33,"tournamentPlayed":15},{"playerId":"e858","ranking":682,"points":32,"tournamentPlayed":23},{"playerId":"o513","ranking":145,"points":394,"tournamentPlayed":26},{"playerId":"f703","ranking":794,"points":21,"tournamentPlayed":15},{"playerId":"g820","ranking":589,"points":50,"tournamentPlayed":22},{"playerId":"sl51","ranking":812,"points":20,"tournamentPlayed":15},{"playerId":"kb95","ranking":205,"points":261,"tournamentPlayed":16},{"playerId":"pe00","ranking":582,"points":51,"tournamentPlayed":18},{"playerId":"kb92","ranking":478,"points":72,"tournamentPlayed":13},{"playerId":"z301","ranking":601,"points":47,"tournamentPlayed":21},{"playerId":"pe02","ranking":274,"points":185,"tournamentPlayed":26},{"playerId":"sn94","ranking":802,"points":21,"tournamentPlayed":21},{"playerId":"lc88","ranking":985,"points":11,"tournamentPlayed":19},{"playerId":"h917","ranking":971,"points":11,"tournamentPlayed":11},{"playerId":"y211","ranking":698,"points":30,"tournamentPlayed":15},{"playerId":"cc32","ranking":218,"points":241,"tournamentPlayed":26},{"playerId":"bd80","ranking":224,"points":234,"tournamentPlayed":27},{"playerId":"mq06","ranking":960,"points":12,"tournamentPlayed":21},{"playerId":"g822","ranking":994,"points":10,"tournamentPlayed":3},{"playerId":"f974","ranking":827,"points":19,"tournamentPlayed":9},{"playerId":"e873","ranking":131,"points":444,"tournamentPlayed":25},{"playerId":"pg32","ranking":208,"points":253,"tournamentPlayed":22},{"playerId":"kb81","ranking":843,"points":19,"tournamentPlayed":34},{"playerId":"ce60","ranking":560,"points":54,"tournamentPlayed":19},{"playerId":"ac84","ranking":671,"points":33,"tournamentPlayed":5},{"playerId":"f724","ranking":62,"points":825,"tournamentPlayed":25},{"playerId":"d787","ranking":993,"points":10,"tournamentPlayed":2},{"playerId":"f965","ranking":413,"points":93,"tournamentPlayed":23},{"playerId":"mb53","ranking":128,"points":446,"tournamentPlayed":23},{"playerId":"f510","ranking":22,"points":1850,"tournamentPlayed":24},{"playerId":"e661","ranking":386,"points":105,"tournamentPlayed":19},{"playerId":"f751","ranking":459,"points":78,"tournamentPlayed":16},{"playerId":"y235","ranking":854,"points":18,"tournamentPlayed":21},{"playerId":"pg69","ranking":421,"points":91,"tournamentPlayed":26},{"playerId":"ca12","ranking":95,"points":580,"tournamentPlayed":24},{"playerId":"cc54","ranking":471,"points":75,"tournamentPlayed":20},{"playerId":"o327","ranking":427,"points":88,"tournamentPlayed":12},{"playerId":"g602","ranking":660,"points":35,"tournamentPlayed":11},{"playerId":"pi95","ranking":424,"points":90,"tournamentPlayed":24},{"playerId":"sj22","ranking":160,"points":344,"tournamentPlayed":30},{"playerId":"pi96","ranking":990,"points":11,"tournamentPlayed":22},{"playerId":"h924","ranking":382,"points":105,"tournamentPlayed":9},{"playerId":"la54","ranking":641,"points":40,"tournamentPlayed":27},{"playerId":"h928","ranking":972,"points":11,"tournamentPlayed":11},{"playerId":"ce77","ranking":302,"points":161,"tournamentPlayed":31},{"playerId":"sl66","ranking":783,"points":23,"tournamentPlayed":25},{"playerId":"pg56","ranking":882,"points":16,"tournamentPlayed":14},{"playerId":"sj25","ranking":896,"points":15,"tournamentPlayed":12},{"playerId":"mu94","ranking":180,"points":307,"tournamentPlayed":24},{"playerId":"mu93","ranking":934,"points":13,"tournamentPlayed":17},{"playerId":"r822","ranking":628,"points":42,"tournamentPlayed":9},{"playerId":"y218","ranking":135,"points":432,"tournamentPlayed":25},{"playerId":"f747","ranking":764,"points":24,"tournamentPlayed":16},{"playerId":"e655","ranking":716,"points":27,"tournamentPlayed":6},{"playerId":"sl94","ranking":456,"points":80,"tournamentPlayed":25},{"playerId":"f774","ranking":545,"points":58,"tournamentPlayed":25},{"playerId":"sj55","ranking":225,"points":233,"tournamentPlayed":17},{"playerId":"bo10","ranking":513,"points":65,"tournamentPlayed":20},{"playerId":"t0a8","ranking":761,"points":24,"tournamentPlayed":9},{"playerId":"z349","ranking":891,"points":15,"tournamentPlayed":5},{"playerId":"sl92","ranking":440,"points":84,"tournamentPlayed":18},{"playerId":"pe42","ranking":950,"points":12,"tournamentPlayed":12},{"playerId":"pc09","ranking":611,"points":45,"tournamentPlayed":11},{"playerId":"cc66","ranking":226,"points":232,"tournamentPlayed":30},{"playerId":"ca33","ranking":325,"points":146,"tournamentPlayed":21},{"playerId":"r612","ranking":162,"points":338,"tournamentPlayed":27},{"playerId":"o340","ranking":305,"points":160,"tournamentPlayed":29},{"playerId":"g628","ranking":33,"points":1375,"tournamentPlayed":22},{"playerId":"e687","ranking":422,"points":90,"tournamentPlayed":11},{"playerId":"e688","ranking":309,"points":158,"tournamentPlayed":28},{"playerId":"bs86","ranking":446,"points":82,"tournamentPlayed":14},{"playerId":"f762","ranking":840,"points":19,"tournamentPlayed":24},{"playerId":"sl85","ranking":598,"points":48,"tournamentPlayed":24},{"playerId":"sl81","ranking":756,"points":25,"tournamentPlayed":22},{"playerId":"df88","ranking":675,"points":33,"tournamentPlayed":19},{"playerId":"pe39","ranking":944,"points":12,"tournamentPlayed":10},{"playerId":"df92","ranking":399,"points":98,"tournamentPlayed":22},{"playerId":"hh06","ranking":605,"points":46,"tournamentPlayed":21},{"playerId":"hh08","ranking":997,"points":10,"tournamentPlayed":7},{"playerId":"g858","ranking":195,"points":278,"tournamentPlayed":15},{"playerId":"e678","ranking":533,"points":59,"tournamentPlayed":17},{"playerId":"h940","ranking":44,"points":1105,"tournamentPlayed":25},{"playerId":"e224","ranking":139,"points":412,"tournamentPlayed":26},{"playerId":"z366","ranking":570,"points":53,"tournamentPlayed":24},{"playerId":"rg42","ranking":610,"points":45,"tournamentPlayed":10},{"playerId":"sh37","ranking":377,"points":108,"tournamentPlayed":21},{"playerId":"z363","ranking":744,"points":26,"tournamentPlayed":24},{"playerId":"pc29","ranking":935,"points":13,"tournamentPlayed":18},{"playerId":"cc98","ranking":307,"points":159,"tournamentPlayed":27},{"playerId":"sy42","ranking":866,"points":17,"tournamentPlayed":19},{"playerId":"wa98","ranking":925,"points":13,"tournamentPlayed":9},{"playerId":"f786","ranking":405,"points":96,"tournamentPlayed":18},{"playerId":"z355","ranking":4,"points":4450,"tournamentPlayed":24},{"playerId":"la94","ranking":320,"points":149,"tournamentPlayed":23},{"playerId":"pg94","ranking":223,"points":236,"tournamentPlayed":27},{"playerId":"e690","ranking":79,"points":697,"tournamentPlayed":20},{"playerId":"pc11","ranking":59,"points":864,"tournamentPlayed":24},{"playerId":"y268","ranking":394,"points":100,"tournamentPlayed":15},{"playerId":"z350","ranking":915,"points":14,"tournamentPlayed":17},{"playerId":"ge00","ranking":967,"points":11,"tournamentPlayed":8},{"playerId":"mo12","ranking":855,"points":18,"tournamentPlayed":21},{"playerId":"sy31","ranking":639,"points":40,"tournamentPlayed":19},{"playerId":"db32","ranking":820,"points":20,"tournamentPlayed":27},{"playerId":"hh26","ranking":368,"points":114,"tournamentPlayed":26},{"playerId":"sy30","ranking":964,"points":11,"tournamentPlayed":5},{"playerId":"r862","ranking":791,"points":21,"tournamentPlayed":7},{"playerId":"la93","ranking":214,"points":249,"tournamentPlayed":27},{"playerId":"e698","ranking":114,"points":502,"tournamentPlayed":30},{"playerId":"h756","ranking":42,"points":1175,"tournamentPlayed":30},{"playerId":"o390","ranking":893,"points":15,"tournamentPlayed":6},{"playerId":"db59","ranking":201,"points":266,"tournamentPlayed":23},{"playerId":"mm10","ranking":479,"points":72,"tournamentPlayed":14},{"playerId":"re27","ranking":953,"points":12,"tournamentPlayed":14},{"playerId":"ge33","ranking":283,"points":176,"tournamentPlayed":23},{"playerId":"mo44","ranking":242,"points":214,"tournamentPlayed":32},{"playerId":"ea13","ranking":523,"points":62,"tournamentPlayed":29},{"playerId":"w09g","ranking":657,"points":35,"tournamentPlayed":5},{"playerId":"sy67","ranking":879,"points":16,"tournamentPlayed":11},{"playerId":"db64","ranking":705,"points":29,"tournamentPlayed":17},{"playerId":"ge28","ranking":287,"points":173,"tournamentPlayed":31},{"playerId":"db63","ranking":90,"points":626,"tournamentPlayed":27},{"playerId":"ca71","ranking":425,"points":89,"tournamentPlayed":20},{"playerId":"o388","ranking":881,"points":16,"tournamentPlayed":14},{"playerId":"bm19","ranking":612,"points":45,"tournamentPlayed":13},{"playerId":"cn08","ranking":738,"points":26,"tournamentPlayed":18},{"playerId":"h996","ranking":80,"points":690,"tournamentPlayed":22},{"playerId":"r419","ranking":163,"points":336,"tournamentPlayed":26},{"playerId":"h997","ranking":115,"points":501,"tournamentPlayed":24},{"playerId":"bm17","ranking":441,"points":84,"tournamentPlayed":24},{"playerId":"f324","ranking":2,"points":9605,"tournamentPlayed":17},{"playerId":"bm03","ranking":374,"points":110,"tournamentPlayed":25},{"playerId":"g892","ranking":331,"points":143,"tournamentPlayed":16},{"playerId":"a09t","ranking":861,"points":17,"tournamentPlayed":13},{"playerId":"pc33","ranking":743,"points":26,"tournamentPlayed":22},{"playerId":"z371","ranking":339,"points":134,"tournamentPlayed":16},{"playerId":"mo41","ranking":529,"points":60,"tournamentPlayed":16},{"playerId":"o376","ranking":177,"points":311,"tournamentPlayed":26},{"playerId":"mq75","ranking":213,"points":249,"tournamentPlayed":23},{"playerId":"hh48","ranking":563,"points":54,"tournamentPlayed":24},{"playerId":"ca62","ranking":707,"points":29,"tournamentPlayed":31},{"playerId":"bm05","ranking":817,"points":20,"tournamentPlayed":23},{"playerId":"h986","ranking":850,"points":18,"tournamentPlayed":12},{"playerId":"sh77","ranking":470,"points":76,"tournamentPlayed":16},{"playerId":"z168","ranking":53,"points":952,"tournamentPlayed":31},{"playerId":"pc68","ranking":294,"points":165,"tournamentPlayed":13},{"playerId":"re45","ranking":449,"points":81,"tournamentPlayed":18},{"playerId":"sf36","ranking":450,"points":81,"tournamentPlayed":21},{"playerId":"pc63","ranking":466,"points":78,"tournamentPlayed":26},{"playerId":"re44","ranking":34,"points":1355,"tournamentPlayed":22},{"playerId":"g681","ranking":269,"points":190,"tournamentPlayed":27},{"playerId":"fb18","ranking":608,"points":46,"tournamentPlayed":26},{"playerId":"ea27","ranking":673,"points":33,"tournamentPlayed":13},{"playerId":"ca99","ranking":74,"points":731,"tournamentPlayed":25},{"playerId":"mm24","ranking":908,"points":14,"tournamentPlayed":11},{"playerId":"su06","ranking":706,"points":29,"tournamentPlayed":25},{"playerId":"g676","ranking":332,"points":142,"tournamentPlayed":14},{"playerId":"f586","ranking":83,"points":676,"tournamentPlayed":26},{"playerId":"y061","ranking":94,"points":592,"tournamentPlayed":26},{"playerId":"k0a3","ranking":772,"points":23,"tournamentPlayed":12},{"playerId":"z395","ranking":867,"points":17,"tournamentPlayed":20},{"playerId":"mo55","ranking":387,"points":105,"tournamentPlayed":23},{"playerId":"t840","ranking":67,"points":755,"tournamentPlayed":28},{"playerId":"sy74","ranking":877,"points":16,"tournamentPlayed":10},{"playerId":"z189","ranking":624,"points":43,"tournamentPlayed":4},{"playerId":"j737","ranking":911,"points":14,"tournamentPlayed":13},{"playerId":"tg46","ranking":806,"points":21,"tournamentPlayed":25},{"playerId":"bk12","ranking":480,"points":72,"tournamentPlayed":23},{"playerId":"f375","ranking":930,"points":13,"tournamentPlayed":14},{"playerId":"rc24","ranking":718,"points":27,"tournamentPlayed":10},{"playerId":"s550","ranking":963,"points":11,"tournamentPlayed":2},{"playerId":"ge73","ranking":550,"points":56,"tournamentPlayed":12},{"playerId":"z184","ranking":66,"points":768,"tournamentPlayed":29},{"playerId":"mm54","ranking":494,"points":69,"tournamentPlayed":29},{"playerId":"gc36","ranking":668,"points":34,"tournamentPlayed":17},{"playerId":"v812","ranking":437,"points":85,"tournamentPlayed":18},{"playerId":"mk08","ranking":946,"points":12,"tournamentPlayed":10},{"playerId":"sh91","ranking":389,"points":103,"tournamentPlayed":31},{"playerId":"sh90","ranking":68,"points":755,"tournamentPlayed":31},{"playerId":"bk19","ranking":191,"points":287,"tournamentPlayed":27},{"playerId":"pc78","ranking":295,"points":165,"tournamentPlayed":19},{"playerId":"bk05","ranking":571,"points":52,"tournamentPlayed":11},{"playerId":"bm45","ranking":766,"points":24,"tournamentPlayed":21},{"playerId":"bm43","ranking":502,"points":67,"tournamentPlayed":14},{"playerId":"l908","ranking":824,"points":19,"tournamentPlayed":6},{"playerId":"sf41","ranking":198,"points":271,"tournamentPlayed":27},{"playerId":"tg30","ranking":798,"points":21,"tournamentPlayed":19},{"playerId":"gc17","ranking":544,"points":58,"tournamentPlayed":22},{"playerId":"t868","ranking":670,"points":34,"tournamentPlayed":23},{"playerId":"r685","ranking":221,"points":240,"tournamentPlayed":15},{"playerId":"db93","ranking":546,"points":58,"tournamentPlayed":25},{"playerId":"v0b2","ranking":929,"points":13,"tournamentPlayed":13},{"playerId":"k0ah","ranking":873,"points":16,"tournamentPlayed":7},{"playerId":"sd32","ranking":64,"points":815,"tournamentPlayed":28},{"playerId":"bk35","ranking":681,"points":32,"tournamentPlayed":17},{"playerId":"sf76","ranking":301,"points":161,"tournamentPlayed":14},{"playerId":"f392","ranking":731,"points":26,"tournamentPlayed":5},{"playerId":"gc53","ranking":796,"points":21,"tournamentPlayed":18},{"playerId":"gc54","ranking":323,"points":147,"tournamentPlayed":21},{"playerId":"hb04","ranking":757,"points":25,"tournamentPlayed":23},{"playerId":"hb05","ranking":237,"points":218,"tournamentPlayed":25},{"playerId":"ki48","ranking":973,"points":11,"tournamentPlayed":12},{"playerId":"mm66","ranking":170,"points":321,"tournamentPlayed":25},{"playerId":"v836","ranking":481,"points":72,"tournamentPlayed":26},{"playerId":"v832","ranking":445,"points":82,"tournamentPlayed":10},{"playerId":"a941","ranking":277,"points":183,"tournamentPlayed":21},{"playerId":"a943","ranking":617,"points":45,"tournamentPlayed":22},{"playerId":"te16","ranking":182,"points":307,"tournamentPlayed":26},{"playerId":"k839","ranking":235,"points":221,"tournamentPlayed":21},{"playerId":"g476","ranking":69,"points":755,"tournamentPlayed":29},{"playerId":"bk24","ranking":431,"points":88,"tournamentPlayed":25},{"playerId":"c09t","ranking":880,"points":16,"tournamentPlayed":14},{"playerId":"mm60","ranking":248,"points":206,"tournamentPlayed":26},{"playerId":"n09u","ranking":961,"points":12,"tournamentPlayed":22},{"playerId":"z198","ranking":848,"points":18,"tournamentPlayed":10},{"playerId":"mm58","ranking":57,"points":894,"tournamentPlayed":26},{"playerId":"gc38","ranking":694,"points":30,"tournamentPlayed":5},{"playerId":"v824","ranking":334,"points":141,"tournamentPlayed":30},{"playerId":"mm56","ranking":638,"points":40,"tournamentPlayed":17},{"playerId":"t885","ranking":447,"points":82,"tournamentPlayed":25},{"playerId":"v821","ranking":804,"points":21,"tournamentPlayed":22},{"playerId":"sf62","ranking":120,"points":488,"tournamentPlayed":22},{"playerId":"k834","ranking":108,"points":526,"tournamentPlayed":25},{"playerId":"m0b2","ranking":658,"points":35,"tournamentPlayed":6},{"playerId":"ra24","ranking":708,"points":28,"tournamentPlayed":4},{"playerId":"bk54","ranking":842,"points":19,"tournamentPlayed":29},{"playerId":"v620","ranking":496,"points":68,"tournamentPlayed":18},{"playerId":"bk52","ranking":647,"points":38,"tournamentPlayed":15},{"playerId":"ki74","ranking":204,"points":262,"tournamentPlayed":14},{"playerId":"bm95","ranking":202,"points":265,"tournamentPlayed":24},{"playerId":"hd64","ranking":637,"points":40,"tournamentPlayed":16},{"playerId":"ki71","ranking":740,"points":26,"tournamentPlayed":20},{"playerId":"hb24","ranking":704,"points":29,"tournamentPlayed":17},{"playerId":"ga36","ranking":442,"points":83,"tournamentPlayed":19},{"playerId":"hd67","ranking":296,"points":165,"tournamentPlayed":28},{"playerId":"tc09","ranking":397,"points":99,"tournamentPlayed":23},{"playerId":"hd68","ranking":645,"points":39,"tournamentPlayed":31},{"playerId":"mi11","ranking":351,"points":122,"tournamentPlayed":17},{"playerId":"kg27","ranking":787,"points":22,"tournamentPlayed":17},{"playerId":"ss25","ranking":952,"points":12,"tournamentPlayed":13},{"playerId":"b0c0","ranking":968,"points":11,"tournamentPlayed":8},{"playerId":"mi08","ranking":240,"points":216,"tournamentPlayed":26},{"playerId":"l950","ranking":492,"points":69,"tournamentPlayed":18},{"playerId":"tc00","ranking":746,"points":26,"tournamentPlayed":33},{"playerId":"h355","ranking":262,"points":195,"tournamentPlayed":13},{"playerId":"k863","ranking":367,"points":114,"tournamentPlayed":23},{"playerId":"sf89","ranking":310,"points":158,"tournamentPlayed":28},{"playerId":"cn78","ranking":360,"points":118,"tournamentPlayed":27},{"playerId":"l949","ranking":126,"points":449,"tournamentPlayed":29},{"playerId":"cn76","ranking":936,"points":13,"tournamentPlayed":19},{"playerId":"mk40","ranking":625,"points":43,"tournamentPlayed":8},{"playerId":"ki63","ranking":527,"points":61,"tournamentPlayed":23},{"playerId":"bk40","ranking":124,"points":465,"tournamentPlayed":21},{"playerId":"v850","ranking":568,"points":53,"tournamentPlayed":18},{"playerId":"mi01","ranking":353,"points":121,"tournamentPlayed":27},{"playerId":"mm79","ranking":398,"points":98,"tournamentPlayed":11},{"playerId":"mm78","ranking":509,"points":65,"tournamentPlayed":17},{"playerId":"v846","ranking":919,"points":14,"tournamentPlayed":31},{"playerId":"su55","ranking":47,"points":1031,"tournamentPlayed":24},{"playerId":"te30","ranking":801,"points":21,"tournamentPlayed":21},{"playerId":"l941","ranking":326,"points":146,"tournamentPlayed":24},{"playerId":"hb41","ranking":358,"points":119,"tournamentPlayed":25},{"playerId":"ki95","ranking":179,"points":308,"tournamentPlayed":26},{"playerId":"v883","ranking":651,"points":38,"tournamentPlayed":27},{"playerId":"gc99","ranking":767,"points":24,"tournamentPlayed":23},{"playerId":"hb48","ranking":152,"points":369,"tournamentPlayed":25},{"playerId":"mi33","ranking":391,"points":102,"tournamentPlayed":24},{"playerId":"kg49","ranking":852,"points":18,"tournamentPlayed":19},{"playerId":"v635","ranking":905,"points":15,"tournamentPlayed":29},{"playerId":"w725","ranking":677,"points":33,"tournamentPlayed":25},{"playerId":"j551","ranking":93,"points":596,"tournamentPlayed":26},{"playerId":"b837","ranking":110,"points":519,"tournamentPlayed":20},{"playerId":"su87","ranking":176,"points":313,"tournamentPlayed":21},{"playerId":"j553","ranking":510,"points":65,"tournamentPlayed":17},{"playerId":"l733","ranking":327,"points":145,"tournamentPlayed":25},{"playerId":"ra43","ranking":575,"points":52,"tournamentPlayed":20},{"playerId":"j557","ranking":485,"points":71,"tournamentPlayed":25},{"playerId":"m0bn","ranking":572,"points":52,"tournamentPlayed":13},{"playerId":"sb28","ranking":759,"points":24,"tournamentPlayed":4},{"playerId":"bi23","ranking":167,"points":330,"tournamentPlayed":19},{"playerId":"tc12","ranking":695,"points":30,"tournamentPlayed":7},{"playerId":"hb31","ranking":902,"points":15,"tournamentPlayed":18},{"playerId":"ki82","ranking":585,"points":51,"tournamentPlayed":25},{"playerId":"gc87","ranking":833,"points":19,"tournamentPlayed":19},{"playerId":"gc88","ranking":341,"points":132,"tournamentPlayed":23},{"playerId":"hb35","ranking":378,"points":106,"tournamentPlayed":22},{"playerId":"mk66","ranking":146,"points":392,"tournamentPlayed":28},{"playerId":"gc89","ranking":148,"points":379,"tournamentPlayed":12},{"playerId":"ke05","ranking":584,"points":51,"tournamentPlayed":22},{"playerId":"ga48","ranking":504,"points":67,"tournamentPlayed":21},{"playerId":"mk64","ranking":995,"points":10,"tournamentPlayed":5},{"playerId":"hb28","ranking":871,"points":17,"tournamentPlayed":25},{"playerId":"hb29","ranking":369,"points":112,"tournamentPlayed":14},{"playerId":"v626","ranking":983,"points":11,"tournamentPlayed":18},{"playerId":"fb98","ranking":86,"points":669,"tournamentPlayed":25},{"playerId":"m0ac","ranking":583,"points":51,"tournamentPlayed":20},{"playerId":"tc11","ranking":453,"points":80,"tournamentPlayed":13},{"playerId":"j543","ranking":899,"points":15,"tournamentPlayed":13},{"playerId":"te51","ranking":82,"points":678,"tournamentPlayed":31},{"playerId":"pa97","ranking":530,"points":60,"tournamentPlayed":17},{"playerId":"ga71","ranking":281,"points":179,"tournamentPlayed":27},{"playerId":"ch05","ranking":420,"points":91,"tournamentPlayed":25},{"playerId":"kg72","ranking":580,"points":51,"tournamentPlayed":18},{"playerId":"tc48","ranking":978,"points":11,"tournamentPlayed":16},{"playerId":"ta04","ranking":720,"points":27,"tournamentPlayed":12},{"playerId":"hb64","ranking":106,"points":531,"tournamentPlayed":25},{"playerId":"v664","ranking":385,"points":105,"tournamentPlayed":19},{"playerId":"sq32","ranking":493,"points":69,"tournamentPlayed":28},{"playerId":"mi52","ranking":795,"points":21,"tournamentPlayed":18},{"playerId":"hb67","ranking":260,"points":197,"tournamentPlayed":27},{"playerId":"cl84","ranking":870,"points":17,"tournamentPlayed":23},{"playerId":"ga79","ranking":250,"points":205,"tournamentPlayed":31},{"playerId":"bk92","ranking":129,"points":446,"tournamentPlayed":25},{"playerId":"lf26","ranking":719,"points":27,"tournamentPlayed":12},{"playerId":"ke36","ranking":959,"points":12,"tournamentPlayed":20},{"playerId":"d0a3","ranking":933,"points":13,"tournamentPlayed":16},{"playerId":"mg08","ranking":306,"points":160,"tournamentPlayed":32},{"playerId":"p09z","ranking":553,"points":55,"tournamentPlayed":13},{"playerId":"ke29","ranking":48,"points":1030,"tournamentPlayed":27},{"playerId":"l993","ranking":821,"points":19,"tournamentPlayed":5},{"playerId":"v656","ranking":656,"points":36,"tournamentPlayed":34},{"playerId":"w503","ranking":845,"points":18,"tournamentPlayed":4},{"playerId":"l996","ranking":723,"points":27,"tournamentPlayed":18},{"playerId":"ra62","ranking":614,"points":45,"tournamentPlayed":18},{"playerId":"bi47","ranking":419,"points":91,"tournamentPlayed":23},{"playerId":"p09o","ranking":521,"points":62,"tournamentPlayed":15},{"playerId":"mi43","ranking":97,"points":570,"tournamentPlayed":22},{"playerId":"lh51","ranking":607,"points":46,"tournamentPlayed":26},{"playerId":"hb55","ranking":665,"points":34,"tournamentPlayed":5},{"playerId":"hb59","ranking":629,"points":42,"tournamentPlayed":15},{"playerId":"ss61","ranking":816,"points":20,"tournamentPlayed":22},{"playerId":"ke19","ranking":732,"points":26,"tournamentPlayed":10},{"playerId":"ke17","ranking":15,"points":2395,"tournamentPlayed":20},{"playerId":"i230","ranking":181,"points":307,"tournamentPlayed":26},{"playerId":"v886","ranking":499,"points":68,"tournamentPlayed":27},{"playerId":"v645","ranking":729,"points":27,"tournamentPlayed":24},{"playerId":"ra52","ranking":976,"points":11,"tournamentPlayed":13},{"playerId":"rc96","ranking":232,"points":223,"tournamentPlayed":16},{"playerId":"i236","ranking":189,"points":290,"tournamentPlayed":33},{"playerId":"p09h","ranking":690,"points":31,"tournamentPlayed":21},{"playerId":"l503","ranking":52,"points":955,"tournamentPlayed":34},{"playerId":"l987","ranking":88,"points":652,"tournamentPlayed":26},{"playerId":"ra51","ranking":200,"points":270,"tournamentPlayed":25},{"playerId":"rc93","ranking":703,"points":29,"tournamentPlayed":10},{"playerId":"ta29","ranking":247,"points":207,"tournamentPlayed":19},{"playerId":"ch27","ranking":30,"points":1472,"tournamentPlayed":21},{"playerId":"ga94","ranking":241,"points":215,"tournamentPlayed":23},{"playerId":"mi74","ranking":547,"points":58,"tournamentPlayed":29},{"playerId":"ad04","ranking":888,"points":16,"tournamentPlayed":21},{"playerId":"kc12","ranking":243,"points":213,"tournamentPlayed":27},{"playerId":"lh85","ranking":760,"points":24,"tournamentPlayed":8},{"playerId":"ld05","ranking":602,"points":47,"tournamentPlayed":23},{"playerId":"bv17","ranking":689,"points":31,"tournamentPlayed":20},{"playerId":"pl38","ranking":811,"points":20,"tournamentPlayed":14},{"playerId":"d815","ranking":693,"points":30,"tournamentPlayed":4},{"playerId":"u107","ranking":784,"points":23,"tournamentPlayed":28},{"playerId":"sq48","ranking":468,"points":77,"tournamentPlayed":19},{"playerId":"c723","ranking":790,"points":21,"tournamentPlayed":6},{"playerId":"a789","ranking":573,"points":52,"tournamentPlayed":16},{"playerId":"tc61","ranking":107,"points":529,"tournamentPlayed":26},{"playerId":"ra82","ranking":491,"points":69,"tournamentPlayed":18},{"playerId":"n707","ranking":591,"points":50,"tournamentPlayed":26},{"playerId":"hb71","ranking":219,"points":241,"tournamentPlayed":27},{"playerId":"lh70","ranking":541,"points":58,"tournamentPlayed":19},{"playerId":"bg23","ranking":61,"points":836,"tournamentPlayed":28},{"playerId":"ch12","ranking":284,"points":176,"tournamentPlayed":24},{"playerId":"w522","ranking":968,"points":11,"tournamentPlayed":8},{"playerId":"af32","ranking":696,"points":30,"tournamentPlayed":12},{"playerId":"bi66","ranking":924,"points":13,"tournamentPlayed":8},{"playerId":"w521","ranking":599,"points":47,"tournamentPlayed":11},{"playerId":"lh74","ranking":932,"points":13,"tournamentPlayed":15},{"playerId":"mi69","ranking":434,"points":87,"tournamentPlayed":27},{"playerId":"kc04","ranking":147,"points":386,"tournamentPlayed":27},{"playerId":"d808","ranking":763,"points":24,"tournamentPlayed":15},{"playerId":"m850","ranking":308,"points":158,"tournamentPlayed":14},{"playerId":"ta12","ranking":132,"points":444,"tournamentPlayed":25},{"playerId":"k435","ranking":36,"points":1335,"tournamentPlayed":22},{"playerId":"d801","ranking":35,"points":1341,"tournamentPlayed":23},{"playerId":"j347","ranking":348,"points":125,"tournamentPlayed":23},{"playerId":"ke73","ranking":229,"points":228,"tournamentPlayed":26},{"playerId":"cf07","ranking":633,"points":41,"tournamentPlayed":11},{"playerId":"u134","ranking":222,"points":236,"tournamentPlayed":21},{"playerId":"cf01","ranking":102,"points":543,"tournamentPlayed":31},{"playerId":"kc33","ranking":340,"points":134,"tournamentPlayed":23},{"playerId":"ld22","ranking":473,"points":75,"tournamentPlayed":22},{"playerId":"mg54","ranking":752,"points":25,"tournamentPlayed":8},{"playerId":"ld26","ranking":249,"points":205,"tournamentPlayed":25},{"playerId":"pl64","ranking":904,"points":15,"tournamentPlayed":24},{"playerId":"e928","ranking":722,"points":27,"tournamentPlayed":15},{"playerId":"n731","ranking":714,"points":28,"tournamentPlayed":27},{"playerId":"i286","ranking":836,"points":19,"tournamentPlayed":20},{"playerId":"l797","ranking":99,"points":561,"tournamentPlayed":26},{"playerId":"ta46","ranking":169,"points":321,"tournamentPlayed":22},{"playerId":"n732","ranking":156,"points":347,"tournamentPlayed":12},{"playerId":"j378","ranking":548,"points":58,"tournamentPlayed":29},{"playerId":"n974","ranking":711,"points":28,"tournamentPlayed":14},{"playerId":"g09c","ranking":603,"points":47,"tournamentPlayed":26},{"playerId":"b896","ranking":519,"points":62,"tournamentPlayed":6},{"playerId":"n729","ranking":535,"points":59,"tournamentPlayed":20},{"playerId":"tc78","ranking":769,"points":24,"tournamentPlayed":26},{"playerId":"bg48","ranking":813,"points":20,"tournamentPlayed":16},{"playerId":"pl56","ranking":153,"points":356,"tournamentPlayed":21},{"playerId":"ke64","ranking":158,"points":346,"tournamentPlayed":30},{"playerId":"lf59","ranking":956,"points":12,"tournamentPlayed":16},{"playerId":"kc29","ranking":87,"points":660,"tournamentPlayed":27},{"playerId":"bi81","ranking":245,"points":209,"tournamentPlayed":21},{"playerId":"me05","ranking":335,"points":139,"tournamentPlayed":18},{"playerId":"mg47","ranking":393,"points":100,"tournamentPlayed":11},{"playerId":"v691","ranking":604,"points":47,"tournamentPlayed":27},{"playerId":"so20","ranking":556,"points":55,"tournamentPlayed":22},{"playerId":"ke69","ranking":407,"points":96,"tournamentPlayed":25},{"playerId":"u120","ranking":330,"points":144,"tournamentPlayed":36},{"playerId":"m873","ranking":101,"points":547,"tournamentPlayed":21},{"playerId":"bv27","ranking":505,"points":67,"tournamentPlayed":22},{"playerId":"bv24","ranking":564,"points":54,"tournamentPlayed":28},{"playerId":"bv25","ranking":593,"points":49,"tournamentPlayed":30},{"playerId":"c977","ranking":3,"points":4960,"tournamentPlayed":21},{"playerId":"b884","ranking":119,"points":494,"tournamentPlayed":29},{"playerId":"mv14","ranking":488,"points":70,"tournamentPlayed":14},{"playerId":"va08","ranking":552,"points":56,"tournamentPlayed":28},{"playerId":"me31","ranking":210,"points":251,"tournamentPlayed":21},{"playerId":"kc51","ranking":627,"points":43,"tournamentPlayed":16},{"playerId":"sq97","ranking":532,"points":60,"tournamentPlayed":33},{"playerId":"kc56","ranking":518,"points":63,"tournamentPlayed":9},{"playerId":"ad41","ranking":834,"points":19,"tournamentPlayed":19},{"playerId":"w571","ranking":251,"points":201,"tournamentPlayed":23},{"playerId":"bg72","ranking":329,"points":144,"tournamentPlayed":23},{"playerId":"lb07","ranking":404,"points":96,"tournamentPlayed":17},{"playerId":"f0a3","ranking":999,"points":10,"tournamentPlayed":8},{"playerId":"so49","ranking":464,"points":78,"tournamentPlayed":24},{"playerId":"l575","ranking":84,"points":674,"tournamentPlayed":22},{"playerId":"sm09","ranking":554,"points":55,"tournamentPlayed":18},{"playerId":"j397","ranking":133,"points":442,"tournamentPlayed":17},{"playerId":"i067","ranking":652,"points":37,"tournamentPlayed":21},{"playerId":"e702","ranking":713,"points":28,"tournamentPlayed":21},{"playerId":"e701","ranking":596,"points":48,"tournamentPlayed":16},{"playerId":"sq80","ranking":159,"points":344,"tournamentPlayed":23},{"playerId":"ka00","ranking":268,"points":191,"tournamentPlayed":25},{"playerId":"r09x","ranking":500,"points":67,"tournamentPlayed":6},{"playerId":"pl78","ranking":781,"points":23,"tournamentPlayed":22},{"playerId":"ch52","ranking":709,"points":28,"tournamentPlayed":12},{"playerId":"pj32","ranking":655,"points":36,"tournamentPlayed":20},{"playerId":"j380","ranking":155,"points":350,"tournamentPlayed":24},{"playerId":"i295","ranking":715,"points":28,"tournamentPlayed":30},{"playerId":"j386","ranking":49,"points":975,"tournamentPlayed":26},{"playerId":"n982","ranking":576,"points":52,"tournamentPlayed":21},{"playerId":"n503","ranking":231,"points":226,"tournamentPlayed":23},{"playerId":"tc95","ranking":439,"points":84,"tournamentPlayed":13},{"playerId":"mc10","ranking":21,"points":1960,"tournamentPlayed":15},{"playerId":"w597","ranking":679,"points":32,"tournamentPlayed":15},{"playerId":"sm37","ranking":24,"points":1810,"tournamentPlayed":27},{"playerId":"be54","ranking":116,"points":498,"tournamentPlayed":24},{"playerId":"u174","ranking":751,"points":25,"tournamentPlayed":7},{"playerId":"mc18","ranking":800,"points":21,"tournamentPlayed":20},{"playerId":"u176","ranking":868,"points":17,"tournamentPlayed":20},{"playerId":"cd00","ranking":444,"points":83,"tournamentPlayed":25},{"playerId":"n771","ranking":113,"points":503,"tournamentPlayed":19},{"playerId":"ch90","ranking":555,"points":55,"tournamentPlayed":19},{"playerId":"g909","ranking":664,"points":35,"tournamentPlayed":32},{"playerId":"gj05","ranking":920,"points":13,"tournamentPlayed":5},{"playerId":"d875","ranking":5,"points":4425,"tournamentPlayed":22},{"playerId":"va22","ranking":912,"points":14,"tournamentPlayed":13},{"playerId":"f811","ranking":109,"points":523,"tournamentPlayed":29},{"playerId":"e720","ranking":777,"points":23,"tournamentPlayed":20},{"playerId":"d874","ranking":70,"points":755,"tournamentPlayed":20},{"playerId":"d632","ranking":121,"points":483,"tournamentPlayed":19},{"playerId":"v490","ranking":239,"points":217,"tournamentPlayed":33},{"playerId":"wb08","ranking":349,"points":124,"tournamentPlayed":19},{"playerId":"ka22","ranking":266,"points":193,"tournamentPlayed":24},{"playerId":"sm25","ranking":8,"points":2880,"tournamentPlayed":22},{"playerId":"ab17","ranking":472,"points":75,"tournamentPlayed":21},{"playerId":"v495","ranking":288,"points":170,"tournamentPlayed":21},{"playerId":"v494","ranking":702,"points":29,"tournamentPlayed":9},{"playerId":"ab12","ranking":892,"points":15,"tournamentPlayed":6},{"playerId":"n763","ranking":886,"points":16,"tournamentPlayed":21},{"playerId":"w579","ranking":291,"points":168,"tournamentPlayed":20},{"playerId":"d868","ranking":630,"points":42,"tournamentPlayed":22},{"playerId":"p701","ranking":528,"points":60,"tournamentPlayed":2},{"playerId":"d864","ranking":72,"points":739,"tournamentPlayed":28},{"playerId":"pf00","ranking":939,"points":12,"tournamentPlayed":1},{"playerId":"so96","ranking":581,"points":51,"tournamentPlayed":18},{"playerId":"pf03","ranking":885,"points":16,"tournamentPlayed":20},{"playerId":"w373","ranking":890,"points":15,"tournamentPlayed":3},{"playerId":"n555","ranking":379,"points":106,"tournamentPlayed":13},{"playerId":"n552","ranking":27,"points":1655,"tournamentPlayed":20},{"playerId":"n558","ranking":383,"points":105,"tournamentPlayed":18},{"playerId":"wb32","ranking":311,"points":157,"tournamentPlayed":16},{"playerId":"g922","ranking":356,"points":120,"tournamentPlayed":24},{"playerId":"r913","ranking":380,"points":106,"tournamentPlayed":19},{"playerId":"o408","ranking":187,"points":297,"tournamentPlayed":25},{"playerId":"u182","ranking":849,"points":18,"tournamentPlayed":11},{"playerId":"kc86","ranking":171,"points":319,"tournamentPlayed":20},{"playerId":"me64","ranking":623,"points":43,"tournamentPlayed":4},{"playerId":"va38","ranking":938,"points":13,"tournamentPlayed":26},{"playerId":"be69","ranking":462,"points":78,"tournamentPlayed":23},{"playerId":"cf59","ranking":76,"points":728,"tournamentPlayed":29},{"playerId":"be67","ranking":77,"points":703,"tournamentPlayed":22},{"playerId":"ka46","ranking":721,"points":27,"tournamentPlayed":13},{"playerId":"be68","ranking":234,"points":222,"tournamentPlayed":29},{"playerId":"w367","ranking":13,"points":2475,"tournamentPlayed":15},{"playerId":"sk06","ranking":874,"points":16,"tournamentPlayed":9},{"playerId":"dg44","ranking":987,"points":11,"tournamentPlayed":19},{"playerId":"sk02","ranking":620,"points":45,"tournamentPlayed":29},{"playerId":"so86","ranking":650,"points":38,"tournamentPlayed":27},{"playerId":"ab40","ranking":692,"points":31,"tournamentPlayed":26},{"playerId":"cf60","ranking":435,"points":86,"tournamentPlayed":15},{"playerId":"wb25","ranking":588,"points":50,"tournamentPlayed":21},{"playerId":"d646","ranking":403,"points":96,"tournamentPlayed":2},{"playerId":"o635","ranking":503,"points":67,"tournamentPlayed":20},{"playerId":"o634","ranking":914,"points":14,"tournamentPlayed":16},{"playerId":"f824","ranking":983,"points":11,"tournamentPlayed":18},{"playerId":"bt45","ranking":621,"points":44,"tournamentPlayed":4},{"playerId":"bt42","ranking":683,"points":32,"tournamentPlayed":24},{"playerId":"d643","ranking":14,"points":2470,"tournamentPlayed":15},{"playerId":"sk30","ranking":979,"points":11,"tournamentPlayed":17},{"playerId":"c582","ranking":415,"points":92,"tournamentPlayed":17},{"playerId":"g940","ranking":285,"points":174,"tournamentPlayed":12},{"playerId":"ph64","ranking":347,"points":126,"tournamentPlayed":25},{"playerId":"bt72","ranking":539,"points":58,"tournamentPlayed":7},{"playerId":"lb66","ranking":304,"points":160,"tournamentPlayed":26},{"playerId":"cf88","ranking":448,"points":81,"tournamentPlayed":13},{"playerId":"ab67","ranking":917,"points":14,"tournamentPlayed":23},{"playerId":"o660","ranking":538,"points":59,"tournamentPlayed":23},{"playerId":"l397","ranking":37,"points":1295,"tournamentPlayed":25},{"playerId":"o423","ranking":432,"points":88,"tournamentPlayed":34},{"playerId":"dg80","ranking":980,"points":11,"tournamentPlayed":17},{"playerId":"ab71","ranking":414,"points":92,"tournamentPlayed":16},{"playerId":"o664","ranking":562,"points":54,"tournamentPlayed":21},{"playerId":"g949","ranking":838,"points":19,"tournamentPlayed":21},{"playerId":"z419","ranking":271,"points":190,"tournamentPlayed":35},{"playerId":"e768","ranking":372,"points":112,"tournamentPlayed":28},{"playerId":"e766","ranking":506,"points":66,"tournamentPlayed":11},{"playerId":"lb51","ranking":497,"points":68,"tournamentPlayed":18},{"playerId":"me82","ranking":25,"points":1670,"tournamentPlayed":27},{"playerId":"f840","ranking":742,"points":26,"tournamentPlayed":22},{"playerId":"me89","ranking":227,"points":230,"tournamentPlayed":17},{"playerId":"dg67","ranking":857,"points":18,"tournamentPlayed":23},{"playerId":"dg65","ranking":712,"points":28,"tournamentPlayed":18},{"playerId":"ab54","ranking":894,"points":15,"tournamentPlayed":8},{"playerId":"n561","ranking":275,"points":184,"tournamentPlayed":35},{"playerId":"be90","ranking":111,"points":518,"tournamentPlayed":24},{"playerId":"o411","ranking":338,"points":136,"tournamentPlayed":25},{"playerId":"n563","ranking":454,"points":80,"tournamentPlayed":15},{"playerId":"gj37","ranking":259,"points":197,"tournamentPlayed":21},{"playerId":"f849","ranking":797,"points":21,"tournamentPlayed":18},{"playerId":"o659","ranking":986,"points":11,"tournamentPlayed":19},{"playerId":"e757","ranking":363,"points":116,"tournamentPlayed":22},{"playerId":"bt68","ranking":371,"points":112,"tournamentPlayed":25},{"playerId":"g935","ranking":319,"points":149,"tournamentPlayed":21},{"playerId":"bt64","ranking":699,"points":30,"tournamentPlayed":18},{"playerId":"lb84","ranking":362,"points":117,"tournamentPlayed":20},{"playerId":"sk51","ranking":508,"points":66,"tournamentPlayed":29},{"playerId":"z443","ranking":841,"points":19,"tournamentPlayed":26},{"playerId":"ma30","ranking":28,"points":1535,"tournamentPlayed":22},{"playerId":"sk53","ranking":619,"points":45,"tournamentPlayed":27},{"playerId":"ka98","ranking":164,"points":335,"tournamentPlayed":22},{"playerId":"ma38","ranking":511,"points":65,"tournamentPlayed":18},{"playerId":"rh25","ranking":898,"points":15,"tournamentPlayed":13},{"playerId":"rh24","ranking":609,"points":45,"tournamentPlayed":6},{"playerId":"pd07","ranking":85,"points":673,"tournamentPlayed":25},{"playerId":"dg97","ranking":878,"points":16,"tournamentPlayed":11},{"playerId":"n598","ranking":498,"points":68,"tournamentPlayed":21},{"playerId":"ab90","ranking":883,"points":16,"tournamentPlayed":17},{"playerId":"mp01","ranking":173,"points":316,"tournamentPlayed":23},{"playerId":"o449","ranking":136,"points":432,"tournamentPlayed":25},{"playerId":"o207","ranking":579,"points":51,"tournamentPlayed":14},{"playerId":"g967","ranking":63,"points":816,"tournamentPlayed":21},{"playerId":"g725","ranking":265,"points":194,"tournamentPlayed":14},{"playerId":"g710","ranking":125,"points":462,"tournamentPlayed":25},{"playerId":"sk41","ranking":328,"points":144,"tournamentPlayed":22},{"playerId":"d683","ranking":9,"points":2815,"tournamentPlayed":20},{"playerId":"h804","ranking":418,"points":91,"tournamentPlayed":11},{"playerId":"lb78","ranking":825,"points":19,"tournamentPlayed":7},{"playerId":"ph71","ranking":282,"points":178,"tournamentPlayed":24},{"playerId":"mc65","ranking":43,"points":1175,"tournamentPlayed":19},{"playerId":"lb76","ranking":516,"points":64,"tournamentPlayed":24},{"playerId":"pf39","ranking":16,"points":2335,"tournamentPlayed":24},{"playerId":"h808","ranking":643,"points":39,"tournamentPlayed":8},{"playerId":"sk48","ranking":962,"points":12,"tournamentPlayed":23},{"playerId":"x015","ranking":810,"points":20,"tournamentPlayed":14},{"playerId":"ph77","ranking":745,"points":26,"tournamentPlayed":30},{"playerId":"pf36","ranking":477,"points":73,"tournamentPlayed":24},{"playerId":"bc68","ranking":734,"points":26,"tournamentPlayed":12},{"playerId":"rh13","ranking":771,"points":23,"tournamentPlayed":12},{"playerId":"ph78","ranking":951,"points":12,"tournamentPlayed":13},{"playerId":"rh16","ranking":122,"points":467,"tournamentPlayed":29},{"playerId":"bc65","ranking":165,"points":330,"tournamentPlayed":19},{"playerId":"sk47","ranking":238,"points":217,"tournamentPlayed":24},{"playerId":"sm88","ranking":517,"points":63,"tournamentPlayed":9},{"playerId":"dg86","ranking":942,"points":12,"tournamentPlayed":4},{"playerId":"bc72","ranking":410,"points":95,"tournamentPlayed":13},{"playerId":"va70","ranking":735,"points":26,"tournamentPlayed":12},{"playerId":"o674","ranking":634,"points":41,"tournamentPlayed":12},{"playerId":"g717","ranking":438,"points":85,"tournamentPlayed":33},{"playerId":"g985","ranking":355,"points":120,"tournamentPlayed":22},{"playerId":"pf65","ranking":185,"points":301,"tournamentPlayed":30},{"playerId":"g983","ranking":151,"points":369,"tournamentPlayed":22},{"playerId":"k09f","ranking":458,"points":78,"tournamentPlayed":15},{"playerId":"si36","ranking":701,"points":29,"tournamentPlayed":3},{"playerId":"t911","ranking":542,"points":58,"tournamentPlayed":20},{"playerId":"r975","ranking":31,"points":1400,"tournamentPlayed":20},{"playerId":"mp20","ranking":350,"points":123,"tournamentPlayed":26},{"playerId":"ba65","ranking":138,"points":428,"tournamentPlayed":30},{"playerId":"o466","ranking":910,"points":14,"tournamentPlayed":13},{"playerId":"gf08","ranking":452,"points":81,"tournamentPlayed":24},{"playerId":"f401","ranking":39,"points":1280,"tournamentPlayed":23},{"playerId":"pf50","ranking":522,"points":62,"tournamentPlayed":21},{"playerId":"sk67","ranking":343,"points":129,"tournamentPlayed":27},{"playerId":"y124","ranking":65,"points":781,"tournamentPlayed":24},{"playerId":"sk69","ranking":359,"points":118,"tournamentPlayed":23},{"playerId":"ba47","ranking":17,"points":2320,"tournamentPlayed":19},{"playerId":"z452","ranking":965,"points":11,"tournamentPlayed":5},{"playerId":"cd85","ranking":10,"points":2705,"tournamentPlayed":26},{"playerId":"gh33","ranking":606,"points":46,"tournamentPlayed":25},{"playerId":"o452","ranking":728,"points":27,"tournamentPlayed":23},{"playerId":"r960","ranking":741,"points":26,"tournamentPlayed":20},{"playerId":"o456","ranking":832,"points":19,"tournamentPlayed":18},{"playerId":"mp13","ranking":430,"points":88,"tournamentPlayed":24},{"playerId":"s0aq","ranking":666,"points":34,"tournamentPlayed":11},{"playerId":"bp29","ranking":839,"points":19,"tournamentPlayed":22},{"playerId":"g978","ranking":927,"points":13,"tournamentPlayed":11},{"playerId":"z246","ranking":314,"points":154,"tournamentPlayed":26},{"playerId":"y152","ranking":676,"points":33,"tournamentPlayed":21},{"playerId":"sk97","ranking":429,"points":88,"tournamentPlayed":17},{"playerId":"co01","ranking":991,"points":11,"tournamentPlayed":22},{"playerId":"z248","ranking":384,"points":105,"tournamentPlayed":19},{"playerId":"sk94","ranking":92,"points":608,"tournamentPlayed":20},{"playerId":"rh62","ranking":916,"points":14,"tournamentPlayed":21},{"playerId":"dc58","ranking":58,"points":878,"tournamentPlayed":26},{"playerId":"ba79","ranking":747,"points":25,"tournamentPlayed":1},{"playerId":"o484","ranking":859,"points":17,"tournamentPlayed":11},{"playerId":"o483","ranking":484,"points":71,"tournamentPlayed":18},{"playerId":"r750","ranking":653,"points":36,"tournamentPlayed":4},{"playerId":"co06","ranking":375,"points":109,"tournamentPlayed":20},{"playerId":"co07","ranking":998,"points":10,"tournamentPlayed":7},{"playerId":"d499","ranking":345,"points":126,"tournamentPlayed":11},{"playerId":"s0dq","ranking":996,"points":10,"tournamentPlayed":7},{"playerId":"rf12","ranking":889,"points":16,"tournamentPlayed":26},{"playerId":"sg01","ranking":955,"points":12,"tournamentPlayed":15},{"playerId":"g753","ranking":290,"points":169,"tournamentPlayed":25},{"playerId":"f664","ranking":346,"points":126,"tournamentPlayed":19},{"playerId":"f663","ranking":748,"points":25,"tournamentPlayed":6},{"playerId":"bp41","ranking":730,"points":27,"tournamentPlayed":25},{"playerId":"pd31","ranking":45,"points":1075,"tournamentPlayed":33},{"playerId":"z239","ranking":590,"points":50,"tournamentPlayed":25},{"playerId":"o482","ranking":203,"points":263,"tournamentPlayed":46},{"playerId":"gf20","ranking":565,"points":54,"tournamentPlayed":31},{"playerId":"n390","ranking":558,"points":54,"tournamentPlayed":15},{"playerId":"rh59","ranking":726,"points":27,"tournamentPlayed":22},{"playerId":"da13","ranking":443,"points":83,"tournamentPlayed":19},{"playerId":"dc51","ranking":918,"points":14,"tournamentPlayed":25},{"playerId":"mr77","ranking":887,"points":16,"tournamentPlayed":21},{"playerId":"v09l","ranking":805,"points":21,"tournamentPlayed":22},{"playerId":"s0ct","ranking":875,"points":16,"tournamentPlayed":9},{"playerId":"k907","ranking":600,"points":47,"tournamentPlayed":16},{"playerId":"si72","ranking":809,"points":20,"tournamentPlayed":12},{"playerId":"k906","ranking":455,"points":80,"tournamentPlayed":24},{"playerId":"y171","ranking":587,"points":50,"tournamentPlayed":21},{"playerId":"pb22","ranking":143,"points":399,"tournamentPlayed":30},{"playerId":"k909","ranking":793,"points":21,"tournamentPlayed":12},{"playerId":"gh92","ranking":654,"points":36,"tournamentPlayed":11},{"playerId":"r772","ranking":20,"points":1985,"tournamentPlayed":30},{"playerId":"gd08","ranking":436,"points":86,"tournamentPlayed":16},{"playerId":"h624","ranking":823,"points":19,"tournamentPlayed":6},{"playerId":"co11","ranking":897,"points":15,"tournamentPlayed":13},{"playerId":"mn20","ranking":376,"points":108,"tournamentPlayed":19},{"playerId":"rh79","ranking":872,"points":16,"tournamentPlayed":2},{"playerId":"sg29","ranking":663,"points":35,"tournamentPlayed":26},{"playerId":"gd01","ranking":862,"points":17,"tournamentPlayed":14},{"playerId":"z254","ranking":166,"points":330,"tournamentPlayed":18},{"playerId":"mn13","ranking":78,"points":702,"tournamentPlayed":29},{"playerId":"dc76","ranking":409,"points":96,"tournamentPlayed":31},{"playerId":"gf36","ranking":856,"points":18,"tournamentPlayed":23},{"playerId":"ba98","ranking":175,"points":313,"tournamentPlayed":17},{"playerId":"da30","ranking":661,"points":35,"tournamentPlayed":17},{"playerId":"da31","ranking":255,"points":199,"tournamentPlayed":18},{"playerId":"mr99","ranking":463,"points":78,"tournamentPlayed":24},{"playerId":"dc70","ranking":974,"points":11,"tournamentPlayed":12},{"playerId":"o498","ranking":858,"points":18,"tournamentPlayed":27},{"playerId":"mp56","ranking":913,"points":14,"tournamentPlayed":14},{"playerId":"sg56","ranking":337,"points":139,"tournamentPlayed":26},{"playerId":"m09h","ranking":807,"points":20,"tournamentPlayed":8},{"playerId":"k926","ranking":75,"points":728,"tournamentPlayed":24},{"playerId":"t982","ranking":236,"points":219,"tournamentPlayed":25},{"playerId":"b09k","ranking":853,"points":18,"tournamentPlayed":20},{"playerId":"m09u","ranking":975,"points":11,"tournamentPlayed":13},{"playerId":"da59","ranking":640,"points":40,"tournamentPlayed":23},{"playerId":"fc36","ranking":864,"points":17,"tournamentPlayed":16},{"playerId":"da67","ranking":264,"points":195,"tournamentPlayed":25},{"playerId":"mn44","ranking":263,"points":195,"tournamentPlayed":24},{"playerId":"h896","ranking":286,"points":173,"tournamentPlayed":27},{"playerId":"bl05","ranking":615,"points":45,"tournamentPlayed":19},{"playerId":"si82","ranking":559,"points":54,"tournamentPlayed":17},{"playerId":"pd74","ranking":779,"points":23,"tournamentPlayed":21},{"playerId":"z272","ranking":280,"points":179,"tournamentPlayed":17},{"playerId":"mp83","ranking":710,"points":28,"tournamentPlayed":14},{"playerId":"fc26","ranking":616,"points":45,"tournamentPlayed":21},{"playerId":"r548","ranking":592,"points":49,"tournamentPlayed":4},{"playerId":"t961","ranking":991,"points":11,"tournamentPlayed":22},{"playerId":"sx50","ranking":487,"points":70,"tournamentPlayed":14}]